codemon/CodemonClean.py
codemon/CodemonFetch.py
codemon/CodemonHelp.py
codemon/CodemonInit.py
codemon/CodemonListen.py
codemon/CodemonMeta.py
codemon/CodemonParse.py
codemon/CodemonReg.py
codemon/__init__.py
codemon/codemon.py
tests/__init__.py
tests/codemoncleantest.py
tests/codemoninitdir.py
tests/index.py
codemon-0.0.2.dist-info/LICENSE
codemon-0.0.2.dist-info/METADATA
codemon-0.0.2.dist-info/WHEEL
codemon-0.0.2.dist-info/entry_points.txt
codemon-0.0.2.dist-info/top_level.txt
codemon-0.0.2.dist-info/RECORD
