Metadata-Version: 2.1
Name: codemon
Version: 0.0.2
Summary: CLI tool to ace competitive programming contests
Home-page: https://github.com/ankingcodes/codemon
Author: Ankush Bhardwaj
Author-email: ankush.bhardwaj0@gmail.com
License: UNKNOWN
Platform: UNKNOWN
Classifier: Programming Language :: Python :: 3
Classifier: License :: OSI Approved :: MIT License
Classifier: Operating System :: OS Independent
Requires-Python: >=3.6
License-File: LICENSE
Requires-Dist: watchdog
Requires-Dist: clint
Requires-Dist: stdiomask
Requires-Dist: requests
Requires-Dist: bs4
